Metadata-Version: 1.0
Name: profanity-filter-awesome
Version: 0.1.0
Summary: Awesome profanity filter
Home-page: UNKNOWN
Author: KamilKujawa
Author-email: super@email.dev
License: UNKNOWN
Platform: UNKNOWN
